elevendoc/__init__.py
elevendoc/main.py
elevendoc/utils.py
elevendoc-1.2.4.dist-info/METADATA
elevendoc-1.2.4.dist-info/WHEEL
elevendoc-1.2.4.dist-info/entry_points.txt
elevendoc-1.2.4.dist-info/top_level.txt
elevendoc-1.2.4.dist-info/RECORD
