Metadata-Version: 2.1
Name: elevendoc
Version: 1.2.4
Summary: Un package pour documenter automatiquement le code
Home-page: https://votre-lien-repo
Author: Matthieu Kaeppelin
Author-email: matthieu.kaeppelin@gmail.com
Classifier: Programming Language :: Python :: 3
Classifier: License :: OSI Approved :: MIT License
Classifier: Operating System :: OS Independent
Requires-Python: >=3.6
Requires-Dist: astunparse==1.6.3
Requires-Dist: langchain==0.3.1
Requires-Dist: azure-identity
Requires-Dist: langchain-community==0.3.1
Requires-Dist: langchain-core==0.3.8
Requires-Dist: python-dotenv==1.0.1
Requires-Dist: requests==2.32.3
Requires-Dist: setuptools==65.5.0
Requires-Dist: black
Requires-Dist: black[jupyter]
Requires-Dist: isort
Requires-Dist: nbformat
Requires-Dist: openai
Requires-Dist: argparse
